examples/__init__.py
terminhtml/__init__.py
terminhtml/__main__.py
terminhtml/_exc.py
terminhtml/ansi_converter.py
terminhtml/base_exc.py
terminhtml/cli.py
terminhtml/cli_docs.py
terminhtml/demo_output.py
terminhtml/exc.py
terminhtml/main.py
terminhtml/output.py
terminhtml/runner/__init__.py
terminhtml/runner/commandresult.py
terminhtml/runner/main.py
tests/__init__.py
tests/config.py
tests/dirutils.py
tests/gen_html.py
tests/test_main.py
tests/test_placeholder.py
tests/test_runner.py
tests/e2e/__init__.py
tests/e2e/cli_stub.py
tests/e2e/ext_click.py
tests/e2e/test_cwd.py
tests/e2e/test_main.py
terminhtml-0.9.3.dist-info/LICENSE.md
terminhtml-0.9.3.dist-info/METADATA
terminhtml-0.9.3.dist-info/WHEEL
terminhtml-0.9.3.dist-info/entry_points.txt
terminhtml-0.9.3.dist-info/top_level.txt
terminhtml-0.9.3.dist-info/RECORD
