Metadata-Version: 2.1
Name: terminhtml
Version: 0.9.3
Summary: Run shell commands and convert into an HTML/CSS animated terminal
Home-page: https://github.com/nickderobertis/terminhtml
Author: Nick DeRobertis
Author-email: derobertis.nick@gmail.com
License: MIT
Project-URL: Code, https://github.com/nickderobertis/terminhtml
Project-URL: Documentation, https://nickderobertis.github.io/terminhtml
Classifier: Development Status :: 3 - Alpha
Classifier: Intended Audience :: Developers
Classifier: Programming Language :: Python :: 3.6
Classifier: Programming Language :: Python :: 3.7
License-File: LICENSE.md
Requires-Dist: ansi2html
Requires-Dist: pydantic
Requires-Dist: pexpect
Requires-Dist: lxml
Requires-Dist: typer
Provides-Extra: demo
Requires-Dist: rich ; extra == 'demo'
